{"nodes":[{"id":6,"title":"L1-a/L3-j","x":256,"y":245,"data":{"type":"generic"}},{"id":7,"title":"L1-b/L2-j/L4-c","x":481,"y":260,"data":{"type":"generic"}},{"id":8,"title":"L1-c/L2-i/L3-d","x":755,"y":277,"data":{"type":"generic"}},{"id":9,"title":"L1-d","x":1042,"y":296,"data":{"type":"generic"}},{"id":10,"title":"L1-e/L2-f","x":1204,"y":307,"data":{"type":"generic"}},{"id":13,"title":"L1-f","x":1401,"y":338,"data":{"type":"generic"}},{"id":14,"title":"L2-a/L3-k","x":239,"y":504,"data":{"type":"generic"}},{"id":15,"title":"L2-b/L4-d","x":473,"y":341,"data":{"type":"generic"}},{"id":16,"title":"L2-c/L4-e","x":640,"y":499,"data":{"type":"generic"}},{"id":17,"title":"L2-d/L3-b","x":899,"y":489,"data":{"type":"generic"}},{"id":18,"title":"L2-e","x":1083,"y":333,"data":{"type":"generic"}},{"id":19,"title":"L2-g","x":1305,"y":67,"data":{"type":"generic"}},{"id":20,"title":"L2-h/L3-e","x":899,"y":101,"data":{"type":"generic"}},{"id":21,"title":"L2-k/L3-i","x":368,"y":73,"data":{"type":"generic"}},{"id":22,"title":"L3-a/L4-f","x":1032,"y":648,"data":{"type":"generic"}},{"id":23,"title":"L3-c","x":675,"y":433,"data":{"type":"generic"}},{"id":24,"title":"L3-f","x":806,"y":-39,"data":{"type":"generic"}},{"id":25,"title":"L3-g/L4-b","x":608,"y":-40,"data":{"type":"generic"}},{"id":26,"title":"L3-h","x":440,"y":-53,"data":{"type":"generic"}},{"id":27,"title":"L3-l","x":316,"y":631,"data":{"type":"generic"}},{"id":28,"title":"L4-a","x":638,"y":122,"data":{"type":"generic"}},{"id":29,"title":"L4-g","x":1223,"y":504,"data":{"type":"generic"}}],"edges":[{"source":6,"target":7},{"source":8,"target":9},{"source":9,"target":10},{"source":10,"target":13},{"source":14,"target":15},{"source":15,"target":16},{"source":16,"target":17},{"source":17,"target":18},{"source":18,"target":10},{"source":10,"target":19},{"source":19,"target":20},{"source":20,"target":8},{"source":7,"target":21},{"source":7,"target":8},{"source":22,"target":17},{"source":17,"target":23},{"source":23,"target":8},{"source":20,"target":24},{"source":24,"target":25},{"source":25,"target":26},{"source":26,"target":21},{"source":21,"target":6},{"source":6,"target":14},{"source":14,"target":27},{"source":28,"target":25},{"source":25,"target":7},{"source":7,"target":15},{"source":16,"target":22},{"source":22,"target":29}],"weakEdges":[]}